nonebot_plugin_easymarkdown/__init__.py
nonebot_plugin_easymarkdown/easy_md_main.py
nonebot_plugin_easymarkdown/test.py1
nonebot_plugin_easymarkdown/to_md.py
nonebot_plugin_easymarkdown-1.0.3.dist-info/LICENSE
nonebot_plugin_easymarkdown-1.0.3.dist-info/METADATA
nonebot_plugin_easymarkdown-1.0.3.dist-info/WHEEL
nonebot_plugin_easymarkdown-1.0.3.dist-info/RECORD
