Metadata-Version: 2.1
Name: nonebot-plugin-easymarkdown
Version: 1.0.3
Summary: 格式化markdown语法，并转化为可读性较好的图片
Author: phquathi
Author-email: yangziqi233@gmail.com
Requires-Python: >=3.8,<4.0
Classifier: Programming Language :: Python :: 3
Classifier: Programming Language :: Python :: 3.8
Classifier: Programming Language :: Python :: 3.9
Classifier: Programming Language :: Python :: 3.10
Classifier: Programming Language :: Python :: 3.11
Classifier: Programming Language :: Python :: 3.12
Requires-Dist: Pillow (>=9.3.0,<10.0.0)
Requires-Dist: PyMuPDF (>=1.22.3,<2.0.0)
Requires-Dist: markdown (>=3.3.7,<4.0.0)
Requires-Dist: markdown2 (>=2.4.2,<3.0.0)
Requires-Dist: nonebot-adapter-onebot (>=2.0.0,<3.0.0)
Requires-Dist: nonebot-plugin-apscheduler (>=0.4.0,<0.5.0)
Requires-Dist: nonebot2 (>=2.0.0,<3.0.0)
Requires-Dist: python-markdown-math (>=0.8.0,<0.9.0)
Requires-Dist: xhtml2pdf (>=0.2.8,<0.3.0)
